awsv4sign.py
aws_v4_signature-2.0.dist-info/LICENSE
aws_v4_signature-2.0.dist-info/METADATA
aws_v4_signature-2.0.dist-info/WHEEL
aws_v4_signature-2.0.dist-info/top_level.txt
aws_v4_signature-2.0.dist-info/RECORD
