Metadata-Version: 2.1
Name: aws-v4-signature
Version: 2.0
Summary: This package will generate AWS V4 authentication Signature for http 1.1 request.
Author-email: Shuaijun Yang <yangshuaijun@outlook.com>
Classifier: Programming Language :: Python :: 3
Classifier: License :: OSI Approved :: Apache Software License
Classifier: Operating System :: OS Independent
Requires-Python: >=3.7
License-File: LICENSE
